<rule>
	<clause type="StringCompare">
		<left-side>
			<source>incomingRequestObjectMethod</source>
			<object>userProfile</object>
			<name>getOrganizationId</name>
		</left-side>
		<operator>EQUALS</operator>
		<right-side>
			<source>constant</source>
			<value>BSC04P</value>
		</right-side>
	</clause>
	<logical-operator>OR</logical-operator>
	<clause type="StringCompare">
		<left-side>
			<source>incomingRequestObjectMethod</source>
			<object>userProfile</object>
			<name>getOrganizationId</name>
		</left-side>
		<operator>EQUALS</operator>
		<right-side>
			<source>constant</source>
			<value>bsc04p</value>
		</right-side>
	</clause>
</rule>
